astraray/utils/__init__.py
astraray/utils/del_jupyter_temp.py
astraray-0.1.1.dist-info/METADATA
astraray-0.1.1.dist-info/WHEEL
astraray-0.1.1.dist-info/entry_points.txt
astraray-0.1.1.dist-info/RECORD
